[
    {
        "id": 1,
        "country": "Україна",
        "city": "Виженка",
        "hotel": "BRB Park Hotel",
        "date": "Літо 2023",
        "description": "Тиша, спокій, шикарні краєвиди. Номери комфортні, є все необхідне, хоча меблі простенькі, але все свіже. Квест добратится з Чернівців. Або рейсовий автобус з минулого століття з автостанції до Виженки, звідти ще якось до готелю (хв 20 пішки з чемоданом або таксі). З Чернівців таксі 1200 грн в один бік і то шукали півтори години – ну не хочуть їхати за місто. Ідеально на своєму авто"
    }
]